{
  "Aak": ["Korean Classical Music"],
  "Acoustic Blues": ["Blues"],
  "Acoustic Chicago Blues": ["Acoustic Blues"],
  "Acoustic Texas Blues": ["Acoustic Blues", "Country Blues"],
  "Alt-Country": ["Country"],
  "Alternative Dance": ["Dance"],
  "Ambient": [],
  "Ambient Americana": ["Ambient"],
  "Ambrosian Chant": ["Plainsong"],
  "Andalusian Classical Music": ["Arabic Classical Music"],
  "Arabic Classical Music": ["Maqāmic Music"],
  "Ars antiqua": ["Medieval Classical Music"],
  "Ars nova": ["Medieval Classical Music"],
  "Ars subtilior": ["Medieval Classical Music"],
  "Art Song": ["Western Classical Music"],
  "Azerbaijani Mugham": ["Maqāmic Music"],
  "Baisha xiyue": ["Chinese Classical Music"],
  "Bakersfield Sound": ["Honky Tonk"],
  "Balinese Gamelan": ["Gamelan"],
  "Ballad Opera": ["Opera"],
  "Ballet": ["Western Classical Music"],
  "Ballet de cour": ["Ballet", "Baroque Music"],
  "Baroque Music": ["Western Classical Music"],
  "Baroque Suite": ["Western Classical Music"],
  "Black Ambient": ["Dark Ambient"],
  "Bluegrass": ["Country"],
  "Bluegrass Gospel": ["Bluegrass", "Country Gospel"],
  "Blues": [],
  "Boogie": ["Disco"],
  "Boogie Woogie": ["Blues"],
  "Brazilian Classical Music": ["Western Classical Music"],
  "British Blues": ["Electric Blues"],
  "Bro-Country": ["Contemporary Country", "Country Pop"],
  "Bubblegum Dance": ["Dance-Pop"],
  "Buganda Royal Court Music": ["Classical Music"],
  "Burmese Classical Music": ["Southeast Asian Classical Music"],
  "Byzantine Chant": ["Byzantine Music"],
  "Byzantine Music": ["Western Classical Music"],
  "Ca trù": ["Vietnamese Classical Music"],
  "Cantata": ["Western Classical Music"],
  "Canto beneventano": ["Plainsong"],
  "Canto mozárabe": ["Plainsong", "Spanish Classical Music"],
  "Cantonese Opera": ["Chinese Opera"],
  "Carnatic Classical Music": ["South Asian Classical Music"],
  "Celtic Chant": ["Plainsong"],
  "Chamber Music": ["Western Classical Music"],
  "Chicago Blues": ["Electric Blues"],
  "Chinese Classical Music": ["East Asian Classical Music"],
  "Chinese Opera": ["Chinese Classical Music"],
  "Choral": ["Western Classical Music"],
  "Choral Concerto": ["Choral"],
  "Choral Symphony": ["Choral", "Symphony"],
  "Cinematic Classical": ["Western Classical Music"],
  "Circus March": ["Classical March"],
  "Classical March": ["Western Classical Music"],
  "Classical Period": ["Western Classical Music"],
  "Close Harmony": ["Traditional Country"],
  "Comédie-ballet": ["Ballet", "Baroque Music"],
  "Concert Band": ["Orchestral Music"],
  "Concerto": ["Orchestral Music"],
  "Concerto for Orchestra": ["Concerto"],
  "Concerto grosso": ["Concerto"],
  "Contemporary Country": ["Country"],
  "Contenance angloise": ["Medieval Classical Music", "Renaissance Music"],
  "Country": [],
  "Country Blues": ["Blues"],
  "Country Boogie": ["Country"],
  "Country Gospel": ["Traditional Country"],
  "Country & Irish": ["Country"],
  "Countrypolitan": ["Country Pop", "Nashville Sound"],
  "Country Pop": ["Country"],
  "Country Yodeling": ["Traditional Country"],
  "Dance": [],
  "Dance-Pop": ["Dance"],
  "Dang-ak": ["Korean Classical Music"],
  "Danmono": ["Sōkyoku"],
  "Dark Ambient": ["Ambient"],
  "Delta Blues": ["Country Blues"],
  "Dhrupad": ["Hindustani Classical Music"],
  "Disco": ["Dance"],
  "Disco polo": ["Dance-Pop"],
  "Divertissement": ["Western Classical Music"],
  "Dobrado": ["Classical March"],
  "Dongjing": ["Chinese Classical Music"],
  "Doskpop": ["Spacesynth"],
  "East Asian Classical Music": ["Classical Music"],
  "Electric Blues": ["Blues"],
  "Electric Texas Blues": ["Electric Blues"],
  "Electro-Disco": ["Disco"],
  "Elizabethan Song": ["Art Song", "Renaissance Music"],
  "Epic Music": ["Cinematic Classical"],
  "Étude": ["Western Classical Music"],
  "Euro-Disco": ["Disco"],
  "Expressionism": ["Modern Classical"],
  "Fantasia": ["Western Classical Music"],
  "Fife and Drum Blues": ["Blues"],
  "Fon leb": ["Thai Classical Music"],
  "Freestyle": ["Dance-Pop"],
  "Fugue": ["Western Classical Music"],
  "Funeral March": ["Classical March"],
  "Funk melody": ["Dance-Pop"],
  "Futurism": ["Modern Classical"],
  "Gagaku": ["Japanese Classical Music"],
  "Gagok": ["Jeong-ak"],
  "Gallican Chant": ["Plainsong"],
  "Gamelan": ["Southeast Asian Classical Music"],
  "Gamelan angklung": ["Balinese Gamelan"],
  "Gamelan beleganjur": ["Balinese Gamelan"],
  "Gamelan degung": ["Gamelan"],
  "Gamelan gender wayang": ["Balinese Gamelan"],
  "Gamelan gong gede": ["Balinese Gamelan"],
  "Gamelan gong kebyar": ["Balinese Gamelan"],
  "Gamelan jegog": ["Balinese Gamelan"],
  "Gamelan sekaten": ["Javanese Gamelan"],
  "Gamelan selonding": ["Balinese Gamelan"],
  "Gamelan semar pegulingan": ["Balinese Gamelan"],
  "Género chico": ["Zarzuela"],
  "Gothic Country": ["Alt-Country"],
  "Grand opéra": ["Opera", "Romanticism"],
  "Grebo": ["Alternative Dance"],
  "Gregorian Chant": ["Plainsong"],
  "Heikyoku": ["Japanese Classical Music"],
  "Henan Opera": ["Chinese Opera"],
  "Hill Country Blues": ["Country Blues"],
  "Hindustani Classical Music": ["South Asian Classical Music"],
  "Hi-NRG": ["Electro-Disco"],
  "Holy Minimalism": ["Minimalism"],
  "Honkyoku": ["Japanese Classical Music"],
  "Honky Tonk": ["Country"],
  "Hyang-ak": ["Korean Classical Music"],
  "Impressionism": ["Modern Classical"],
  "Indeterminacy": ["Modern Classical"],
  "Inkiranya": ["Classical Music"],
  "Integral Serialism": ["Serialism"],
  "Iraqi Maqam": ["Arabic Classical Music"],
  "Italo-Disco": ["Electro-Disco"],
  "Jamgrass": ["Progressive Bluegrass"],
  "Japanese Classical Music": ["East Asian Classical Music"],
  "Javanese Gamelan": ["Gamelan"],
  "Jeong-ak": ["Korean Classical Music"],
  "Jiuta": ["Japanese Classical Music"],
  "Jōruri": ["Japanese Classical Music"],
  "Jug Band": ["Acoustic Blues"],
  "Jump Blues": ["Blues"],
  "Kacapi suling": ["Southeast Asian Classical Music"],
  "Kafi": ["Hindustani Classical Music"],
  "Kalon'ny fahiny": ["Operetta"],
  "Kete": ["Classical Music"],
  "Khayal": ["Hindustani Classical Music"],
  "Khrueang sai": ["Thai Classical Music"],
  "Konnakol": ["Carnatic Classical Music"],
  "Korean Classical Music": ["East Asian Classical Music"],
  "Korean Revolutionary Opera": ["Peking Opera"],
  "Kulintang": ["Southeast Asian Classical Music"],
  "Kumiuta": ["Sōkyoku"],
  "Latin American Classical Music": ["Western Classical Music"],
  "Latin Disco": ["Disco"],
  "Latin Freestyle": ["Freestyle"],
  "Lied": ["Art Song"],
  "Light Music": ["Western Classical Music"],
  "Madrigal": ["Western Classical Music"],
  "Maqāmic Music": ["Classical Music"],
  "Mahori": ["Southeast Asian Classical Music"],
  "Malay Classical Music": ["Southeast Asian Classical Music"],
  "Malay Gamelan": ["Gamelan", "Malay Classical Music"],
  "Mass": ["Choral"],
  "Medieval Classical Music": ["Western Classical Music"],
  "Medieval Lyric Poetry": ["Medieval Classical Music"],
  "Meiji shinkyoku": ["Japanese Classical Music"],
  "Mélodie": ["Art Song"],
  "Microtonal Classical": ["Modern Classical"],
  "Minimalism": ["Modern Classical"],
  "Minyue": ["Classical Music"],
  "Modern Classical": ["Western Classical Music"],
  "Monodrama": ["Opera"],
  "Motet": ["Western Classical Music"],
  "Musique concrète instrumentale": ["Modern Classical"],
  "Mutant Disco": ["Disco"],
  "Nagauta": ["Japanese Classical Music"],
  "Nashville Sound": ["Country"],
  "Neoclassicism": ["Western Classical Music"],
  "Neo-Traditionalist Country": ["Contemporary Country"],
  "New Complexity": ["Modern Classical"],
  "New Orleans Blues": ["Blues"],
  "New Rave": ["Alternative Dance"],
  "Nocturne": ["Western Classical Music"],
  "Noh": ["Japanese Classical Music"],
  "Nu-Disco": ["Disco"],
  "Odissi Classical Music": ["South Asian Classical Music"],
  "Old Roman Chant": ["Plainsong"],
  "Opera": ["Western Classical Music"],
  "Opéra-ballet": ["Ballet", "Baroque Music", "Opera"],
  "Opera buffa": ["Opera"],
  "Opéra-comique": ["Opera"],
  "Opera semiseria": ["Opera"],
  "Opera seria": ["Opera"],
  "Operetta": ["Opera"],
  "Oratorio": ["Western Classical Music"],
  "Orchestral Music": ["Western Classical Music"],
  "Orchestral Song": ["Art Song", "Orchestral Music"],
  "Outlaw Country": ["Progressive Country"],
  "Overture": ["Western Classical Music"],
  "Peking Opera": ["Chinese Opera"],
  "Persian Classical Music": ["Maqāmic Music"],
  "Piano Blues": ["Blues"],
  "Piedmont Blues": ["Acoustic Blues", "Country Blues"],
  "Pinpeat": ["Southeast Asian Classical Music"],
  "Pìobaireachd": ["Classical Music"],
  "Piphat": ["Thai Classical Music"],
  "Plainsong": ["Medieval Classical Music"],
  "Post-Minimalism": ["Modern Classical"],
  "Prelude": ["Western Classical Music"],
  "Progressive Bluegrass": ["Bluegrass"],
  "Progressive Country": ["Country"],
  "Qawwali": ["Hindustani Classical Music"],
  "Red Dirt": ["Country"],
  "Renaissance Music": ["Western Classical Music"],
  "Requiem": ["Mass"],
  "Revolutionary Opera": ["Peking Opera"],
  "Ricercar": ["Western Classical Music"],
  "Ritual Ambient": ["Dark Ambient"],
  "Romanian Popcorn": ["Dance-Pop"],
  "Romanticism": ["Western Classical Music"],
  "Romantische Oper": ["Opera", "Romanticism"],
  "Saluang klasik": ["Southeast Asian Classical Music"],
  "Sarum Chant": ["Gregorian Chant"],
  "Sawt": ["Arabic Classical Music"],
  "Serenade": ["Western Classical Music"],
  "Serialism": ["Modern Classical"],
  "Shabad kirtan": ["Hindustani Classical Music"],
  "Shaoxing Opera": ["Chinese Opera"],
  "Shashmaqam": ["Maqāmic Music"],
  "Shōmyō": ["Japanese Classical Music"],
  "Sinfonia concertante": ["Concerto", "Symphony"],
  "Singspeil": ["Opera"],
  "Sōkyoku": ["Japanse Classical Music"],
  "Sonata": ["Western Classical Music"],
  "Sonorism": ["Modern Classical"],
  "Soul Blues": ["Blues"],
  "South Asian Classical Music": ["Classical Music"],
  "Southeast Asian Classical Music": ["Classical Music"],
  "Space Ambient": ["Ambient"],
  "Space Disco": ["Electro-Disco"],
  "Spacesynth": ["Italo-Disco"],
  "Spaghetti Western": ["Cinematic Classical"],
  "Spanish Classical Music": ["Western Classical Music"],
  "Spectralism": ["Modern Classical"],
  "Stochastic Music": ["Modern Classical"],
  "Sufiana kalam": ["Maqāmic Music"],
  "Swamp Blues": ["Electric Blues"],
  "Symphony": ["Orchestral Music"],
  "Talempong": ["Southeast Asian Classical Music"],
  "Tarana": ["Hindustani Classical Music"],
  "Tecnorumba": ["Dance-Pop"],
  "Tembang Sunda Cianjuran": ["Southeast Asian Classical Music"],
  "Thai Classical Music": ["Southeast Asian Classical Music"],
  "Thumri": ["Hindustani Classical Music"],
  "Tibetan Buddhist Chant": ["Classical Music"],
  "Toccata": ["Western Classical Music"],
  "Tone Poem": ["Orchestral Music"],
  "Totalism": ["Post-Minimalism"],
  "Township Bubblegum": ["Dance-Pop"],
  "Traditional Country": ["Country"],
  "Tragédie en musique": ["Opera"],
  "Tribal Ambient": ["Ambient"],
  "Truck Driving Country": ["Honky Tonk"],
  "Turkish Classical Music": ["Maqāmic Music"],
  "Turkish Mevlevi Music": ["Turkish Classical Music"],
  "Twelve Muqam": ["Maqāmic Music"],
  "Urban Cowboy": ["Country Pop"],
  "Valsa brasileira": ["Brazilian Classical Music"],
  "Vaudeville Blues": ["Blues"],
  "Verismo": ["Opera"],
  "Vietnamese Classical Music": ["East Asian Classical Music"],
  "Vietnamese Opera": ["Vietnamese Classical Music"],
  "Western": ["Country"],
  "Western Classical Music": ["Classical Music"],
  "Western Swing": ["Country"],
  "Yangzhou Opera": ["Chinese Opera"],
  "Yayue": ["Chinese Classical Music"],
  "Zarzuela": ["Opera", "Spanish Classical Music"],
  "Zarzuela barroca": ["Baroque Music", "Zarzuela"],
  "Zarzuela grande": ["Zarzuela"],
  "Zeitoper": ["Opera"]
}